<?xml version="1.0" encoding="utf-8"?>
<static>true</static>
<model>QUAD_3D</model>
<TRANSFORM>
    <Transform>
        <position x="100" y="14.5" z="-50"/>
        <orientation x="-89.8057175" y="4.86804658e-15" z="2.16586387e-18"/>
        <scale x="102.562851" y="102.06208" z="102.613083"/>
    </Transform>
</TRANSFORM>
<BOUNDS>
    <Show__AABB>false</Show__AABB>
    <Show__Bounding__Sphere>false</Show__Bounding__Sphere>
</BOUNDS>
<RENDERING>
    <Material>
        <shadingMode>BLINN_PHONG</shadingMode>
        <colour r="0" g="1" b="0" a="1"/>
        <emissive r="0" g="0.100000001" b="0"/>
        <specular r="0.800000012" g="0.800000012" b="0.800000012"/>
        <shininess>50</shininess>
        <doubleSided>true</doubleSided>
        <receivesShadows>true</receivesShadows>
        <bumpMethod>NONE</bumpMethod>
        <parallaxFactor>0.00999999978</parallaxFactor>
    </Material>
    <Rendered__LOD__Level>0</Rendered__LOD__Level>
    <Lock__LoD>false</Lock__LoD>
    <Lock__LoD__Level>0</Lock__LoD__Level>
</RENDERING>
<NETWORKING/>
<QUAD_3D/>
