<?xml version="1.0" encoding="utf-8"?>
<static>true</static>
<TRANSFORM>
    <Transform>
        <position x="153.156082" y="16.3086472" z="0.418743253"/>
        <orientation x="0" y="-0" z="0"/>
        <scale x="1" y="1" z="1"/>
    </Transform>
</TRANSFORM>
<BOUNDS>
    <Show__AABB>false</Show__AABB>
    <Show__Bounding__Sphere>false</Show__Bounding__Sphere>
</BOUNDS>
<NETWORKING/>
<POINT_LIGHT>
    <Range>10</Range>
    <Intensity>1</Intensity>
    <Colour r="0.03125" g="0.03125" b="1"/>
    <Is__Shadow__Caster>true</Is__Shadow__Caster>
    <Shadow__Bias>0.0250000004</Shadow__Bias>
    <Shadow__Strength>1</Shadow__Strength>
</POINT_LIGHT>
